meloplus/__init__.py
meloplus/api.py
meloplus/app.py
meloplus/attentions.py
meloplus/commons.py
meloplus/data_utils.py
meloplus/download_utils.py
meloplus/infer.py
meloplus/init_downloads.py
meloplus/losses.py
meloplus/main.py
meloplus/mel_processing.py
meloplus/models.py
meloplus/modules.py
meloplus/preprocess_text.py
meloplus/split_utils.py
meloplus/train.py
meloplus/transforms.py
meloplus/utils.py
meloplus/monotonic_align/__init__.py
meloplus/monotonic_align/core.py
meloplus/text/__init__.py
meloplus/text/chinese.py
meloplus/text/chinese_bert.py
meloplus/text/chinese_mix.py
meloplus/text/cleaner.py
meloplus/text/cleaner_multiling.py
meloplus/text/cmudict.rep
meloplus/text/cmudict_cache.pickle
meloplus/text/english.py
meloplus/text/english_bert.py
meloplus/text/french.py
meloplus/text/french_bert.py
meloplus/text/japanese.py
meloplus/text/japanese_bert.py
meloplus/text/ko_dictionary.py
meloplus/text/korean.py
meloplus/text/opencpop-strict.txt
meloplus/text/spanish.py
meloplus/text/spanish_bert.py
meloplus/text/symbols.py
meloplus/text/tone_sandhi.py
meloplus/text/english_utils/__init__.py
meloplus/text/english_utils/abbreviations.py
meloplus/text/english_utils/number_norm.py
meloplus/text/english_utils/time_norm.py
meloplus/text/es_phonemizer/__init__.py
meloplus/text/es_phonemizer/base.py
meloplus/text/es_phonemizer/cleaner.py
meloplus/text/es_phonemizer/es_symbols.json
meloplus/text/es_phonemizer/es_symbols.txt
meloplus/text/es_phonemizer/es_symbols_v2.json
meloplus/text/es_phonemizer/es_to_ipa.py
meloplus/text/es_phonemizer/example_ipa.txt
meloplus/text/es_phonemizer/gruut_wrapper.py
meloplus/text/es_phonemizer/punctuation.py
meloplus/text/es_phonemizer/spanish_symbols.txt
meloplus/text/es_phonemizer/test.ipynb
meloplus/text/fr_phonemizer/__init__.py
meloplus/text/fr_phonemizer/base.py
meloplus/text/fr_phonemizer/cleaner.py
meloplus/text/fr_phonemizer/en_symbols.json
meloplus/text/fr_phonemizer/example_ipa.txt
meloplus/text/fr_phonemizer/fr_symbols.json
meloplus-0.0.7.dist-info/LICENSE
meloplus-0.0.7.dist-info/METADATA
meloplus-0.0.7.dist-info/WHEEL
meloplus-0.0.7.dist-info/top_level.txt
meloplus-0.0.7.dist-info/RECORD
