Metadata-Version: 2.1
Name: meloplus
Version: 0.0.7
Summary: Meloplus: Advanced python library for Melotts
Home-page: https://github.com/kadirnar/meloplus
Author: kadirnar
Author-email: kadir.nar@hotmail.com
License: Apache License 2.0
License-File: LICENSE
Requires-Dist: txtsplit
Requires-Dist: torch
Requires-Dist: torchaudio
Requires-Dist: cached_path
Requires-Dist: num2words==0.5.12
Requires-Dist: unidic_lite==1.0.8
Requires-Dist: unidic==1.1.0
Requires-Dist: mecab-python3==1.0.9
Requires-Dist: pykakasi==2.2.1
Requires-Dist: fugashi==1.3.0
Requires-Dist: g2p_en==2.1.0
Requires-Dist: anyascii==0.3.2
Requires-Dist: jamo==0.4.1
Requires-Dist: gruut[de,es,fr]==2.2.3
Requires-Dist: g2pkk>=0.1.1
Requires-Dist: librosa==0.9.1
Requires-Dist: pydub==0.25.1
Requires-Dist: eng_to_ipa==0.0.2
Requires-Dist: inflect==7.0.0
Requires-Dist: unidecode==1.3.7
Requires-Dist: pypinyin==0.50.0
Requires-Dist: cn2an==0.5.22
Requires-Dist: jieba==0.42.1
Requires-Dist: gradio
Requires-Dist: langid==1.1.6
Requires-Dist: tqdm
Requires-Dist: tensorboard==2.16.2
Requires-Dist: loguru==0.7.2
